{
    "#" : {
        "10 Crosby Derek Lam" : "/search/?m=2&word=10%20Crosby%20Derek%20Lam",
        "2nd Day" : "/search/?m=2&word=2nd%20Day",
        "3.1 Phillip Lim" : "/search/?m=2&word=3.1%20Phillip%20Lim",
        "7 For All Mankind" : "/search/?m=2&word=7%20For%20All%20Mankind",
        "Étoile Isabel Marant" : "/search/?m=2&word=%C3%89toile%20Isabel%20Marant",
        "川久保玲" : "/search/?m=2&word=%E5%B7%9D%E4%B9%85%E4%BF%9D%E7%8E%B2"
    },
    "A" : {
        "A Detacher" : "/search/?m=2&word=A%20Detacher",
        "A.P.C." : "/search/?m=2&word=A.P.C.",
        "ADDISON" : "/search/?m=2&word=ADDISON",
        "ADIDAS" : "/search/?m=2&word=ADIDAS",
        "AG Adriano Goldschmied" : "/search/?m=2&word=AG%20Adriano%20Goldschmied",
        "ALDO" : "/search/?m=2&word=ALDO",
        "ALICE by Temperley" : "/search/?m=2&word=ALICE%20by%20Temperley",
        "ANNA SUI" : "/search/?m=2&word=ANNA%20SUI",
        "ASOS" : "/search/?m=2&word=ASOS",
        "Abercrombie & Fitch" : "/search/?m=2&word=Abercrombie%20%26%20Fitch",
        "Acne" : "/search/?m=2&word=Acne",
        "Acne Studios" : "/search/?m=2&word=Acne%20Studios",
        "Adam Lippes" : "/search/?m=2&word=Adam%20Lippes",
        "Adidas by Stella McCartney" : "/search/?m=2&word=Adidas%20by%20Stella%20McCartney",
        "Akris Punto" : "/search/?m=2&word=Akris%20Punto",
        "Alaïa" : "/search/?m=2&word=Ala%C3%AFa",
        "Alberta Ferretti" : "/search/?m=2&word=Alberta%20Ferretti",
        "Alejandro Ingelmo" : "/search/?m=2&word=Alejandro%20Ingelmo",
        "Alexander McQueen" : "/search/?m=2&word=Alexander%20McQueen",
        "Alexander Wang" : "/search/?m=2&word=Alexander%20Wang",
        "Alice + Olivia" : "/search/?m=2&word=Alice%20%2B%20Olivia",
        "Alice Mccall" : "/search/?m=2&word=Alice%20Mccall",
        "Altuzarra" : "/search/?m=2&word=Altuzarra",
        "Amanda Uprichard" : "/search/?m=2&word=Amanda%20Uprichard",
        "American Apparel" : "/search/?m=2&word=American%20Apparel",
        "American Vintage" : "/search/?m=2&word=American%20Vintage",
        "Ancient Greek Sandals" : "/search/?m=2&word=Ancient%20Greek%20Sandals",
        "Andre Assous" : "/search/?m=2&word=Andre%20Assous",
        "Ann Demeulemeester" : "/search/?m=2&word=Ann%20Demeulemeester",
        "Anna Scholz" : "/search/?m=2&word=Anna%20Scholz",
        "Anndra Neen" : "/search/?m=2&word=Anndra%20Neen",
        "Antipodium" : "/search/?m=2&word=Antipodium",
        "Antonio Berardi" : "/search/?m=2&word=Antonio%20Berardi",
        "Antonioli" : "/search/?m=2&word=Antonioli",
        "Anuschka" : "/search/?m=2&word=Anuschka",
        "Anya Hindmarch" : "/search/?m=2&word=Anya%20Hindmarch",
        "Aperlai" : "/search/?m=2&word=Aperlai",
        "Aqua" : "/search/?m=2&word=Aqua",
        "Aquazzura" : "/search/?m=2&word=Aquazzura",
        "Armani Collezioni" : "/search/?m=2&word=Armani%20Collezioni",
        "Armani Jeans" : "/search/?m=2&word=Armani%20Jeans",
        "Ash" : "/search/?m=2&word=Ash",
        "Ashish" : "/search/?m=2&word=Ashish"
    },
    "B" : {
        "B Brian Atwood" : "/search/?m=2&word=B%20Brian%20Atwood",
        "B-Side" : "/search/?m=2&word=B-Side",
        "BA&SH" : "/search/?m=2&word=BA%26SH",
        "BALLY" : "/search/?m=2&word=BALLY",
        "BB Dakota" : "/search/?m=2&word=BB%20Dakota",
        "BCBGMAXAZRIA" : "/search/?m=2&word=BCBGMAXAZRIA",
        "BLK DNM" : "/search/?m=2&word=BLK%20DNM",
        "BOSS HUGO BOSS" : "/search/?m=2&word=BOSS%20HUGO%20BOSS",
        "BZR" : "/search/?m=2&word=BZR",
        "Badgley Mischka" : "/search/?m=2&word=Badgley%20Mischka",
        "Balenciaga" : "/search/?m=2&word=Balenciaga",
        "Balmain" : "/search/?m=2&word=Balmain",
        "Band of Outsiders" : "/search/?m=2&word=Band%20of%20Outsiders",
        "Banjo & Matilda" : "/search/?m=2&word=Banjo%20%26%20Matilda",
        "Barbour" : "/search/?m=2&word=Barbour",
        "Baum und Pferdgarten" : "/search/?m=2&word=Baum%20und%20Pferdgarten",
        "Bebe" : "/search/?m=2&word=Bebe",
        "Beloved" : "/search/?m=2&word=Beloved",
        "Belstaff" : "/search/?m=2&word=Belstaff",
        "Black Halo" : "/search/?m=2&word=Black%20Halo",
        "Bloomingdale's" : "/search/?m=2&word=Bloomingdale%27s",
        "Bottega Veneta" : "/search/?m=2&word=Bottega%20Veneta",
        "Boutique by Jaeger" : "/search/?m=2&word=Boutique%20by%20Jaeger",
        "Brahmin Atelier" : "/search/?m=2&word=Brahmin%20Atelier",
        "Brunello Cucinelli" : "/search/?m=2&word=Brunello%20Cucinelli",
        "Burberry" : "/search/?m=2&word=Burberry",
        "Burberry Brit" : "/search/?m=2&word=Burberry%20Brit",
        "Burberry London" : "/search/?m=2&word=Burberry%20London",
        "Burberry Prorsum" : "/search/?m=2&word=Burberry%20Prorsum",
        "By Malene Birger" : "/search/?m=2&word=By%20Malene%20Birger"
    },
    "C" : {
        "C&#233;dric Charlier" : "/search/?m=2&word=C%26%23233%3Bdric%20Charlier",
        "CATHERINE MALANDRINO" : "/search/?m=2&word=CATHERINE%20MALANDRINO",
        "CÉLINE" : "/search/?m=2&word=C%C3%89LINE",
        "CHANEL" : "/search/?m=2&word=CHANEL",
        "CHLOÉ" : "/search/?m=2&word=CHLO%C3%89",
        "Calvin Klein" : "/search/?m=2&word=Calvin%20Klein",
        "Camilla" : "/search/?m=2&word=Camilla",
        "Camilla Skovgaard" : "/search/?m=2&word=Camilla%20Skovgaard",
        "Carat" : "/search/?m=2&word=Carat",
        "Carolina Herrera" : "/search/?m=2&word=Carolina%20Herrera",
        "Carvela Kurt Geiger" : "/search/?m=2&word=Carvela%20Kurt%20Geiger",
        "Carven" : "/search/?m=2&word=Carven",
        "Casadei" : "/search/?m=2&word=Casadei",
        "Chalayan" : "/search/?m=2&word=Chalayan",
        "Charlotte Olympia" : "/search/?m=2&word=Charlotte%20Olympia",
        "Cherevichkiotvichki" : "/search/?m=2&word=Cherevichkiotvichki",
        "Chinti and Parker" : "/search/?m=2&word=Chinti%20and%20Parker",
        "Christian Louboutin" : "/search/?m=2&word=Christian%20Louboutin",
        "Christophe Lemaire" : "/search/?m=2&word=Christophe%20Lemaire",
        "Christopher Kane" : "/search/?m=2&word=Christopher%20Kane",
        "Citizens of Humanity" : "/search/?m=2&word=Citizens%20of%20Humanity",
        "Closet" : "/search/?m=2&word=Closet",
        "Clover Canyon" : "/search/?m=2&word=Clover%20Canyon",
        "Clu" : "/search/?m=2&word=Clu",
        "Club Monaco" : "/search/?m=2&word=Club%20Monaco",
        "Coach" : "/search/?m=2&word=Coach",
        "Coast" : "/search/?m=2&word=Coast",
        "Coco Mademoiselle" : "/search/?m=2&word=Coco%20Mademoiselle",
        "Converse" : "/search/?m=2&word=Converse",
        "Courreges" : "/search/?m=2&word=Courreges"
    },
    "D" : {
        "DAY Birger et Mikkelsen" : "/search/?m=2&word=DAY%20Birger%20et%20Mikkelsen",
        "DKNY" : "/search/?m=2&word=DKNY",
        "DL1961" : "/search/?m=2&word=DL1961",
        "DSQUARED2" : "/search/?m=2&word=DSQUARED2",
        "Dagmar" : "/search/?m=2&word=Dagmar",
        "Darling" : "/search/?m=2&word=Darling",
        "David Galan" : "/search/?m=2&word=David%20Galan",
        "Deux Lux" : "/search/?m=2&word=Deux%20Lux",
        "Diane von Furstenberg" : "/search/?m=2&word=Diane%20von%20Furstenberg",
        "Diesel" : "/search/?m=2&word=Diesel",
        "Dior" : "/search/?m=2&word=Dior",
        "Dolce Vita" : "/search/?m=2&word=Dolce%20Vita",
        "Dr. Martens" : "/search/?m=2&word=Dr.%20Martens",
        "Dries Van Noten" : "/search/?m=2&word=Dries%20Van%20Noten"
    },
    "E" : {
        "EDUN" : "/search/?m=2&word=EDUN",
        "ELIE SAAB" : "/search/?m=2&word=ELIE%20SAAB",
        "ELLE" : "/search/?m=2&word=ELLE",
        "ERDEM" : "/search/?m=2&word=ERDEM",
        "Eddie Borgo" : "/search/?m=2&word=Eddie%20Borgo",
        "Edith A. Miller" : "/search/?m=2&word=Edith%20A.%20Miller",
        "Eileen Fisher" : "/search/?m=2&word=Eileen%20Fisher",
        "Ela" : "/search/?m=2&word=Ela",
        "Elie Tahari" : "/search/?m=2&word=Elie%20Tahari",
        "Elizabeth and James" : "/search/?m=2&word=Elizabeth%20and%20James",
        "Emilio Pucci" : "/search/?m=2&word=Emilio%20Pucci",
        "Emma Cook" : "/search/?m=2&word=Emma%20Cook",
        "Emporio Armani" : "/search/?m=2&word=Emporio%20Armani",
        "Equipment" : "/search/?m=2&word=Equipment",
        "Escada" : "/search/?m=2&word=Escada",
        "Esprit" : "/search/?m=2&word=Esprit",
        "Etro" : "/search/?m=2&word=Etro"
    },
    "F" : {
        "FCUK" : "/search/?m=2&word=FCUK",
        "FRAME Denim" : "/search/?m=2&word=FRAME%20Denim",
        "FREEBIRD by Steven" : "/search/?m=2&word=FREEBIRD%20by%20Steven",
        "Faith" : "/search/?m=2&word=Faith",
        "Faith Connexion" : "/search/?m=2&word=Faith%20Connexion",
        "Falabella" : "/search/?m=2&word=Falabella",
        "Fendi" : "/search/?m=2&word=Fendi",
        "Floto" : "/search/?m=2&word=Floto",
        "Folli Follie" : "/search/?m=2&word=Folli%20Follie",
        "Forever Unique" : "/search/?m=2&word=Forever%20Unique",
        "Francesco Biasia" : "/search/?m=2&word=Francesco%20Biasia",
        "Free People" : "/search/?m=2&word=Free%20People",
        "Frye" : "/search/?m=2&word=Frye"
    },
    "G" : {
        "G-Star" : "/search/?m=2&word=G-Star",
        "GUCCI" : "/search/?m=2&word=GUCCI",
        "GUESS" : "/search/?m=2&word=GUESS",
        "Ganni" : "/search/?m=2&word=Ganni",
        "Giambattista Valli" : "/search/?m=2&word=Giambattista%20Valli",
        "Gianvito Rossi" : "/search/?m=2&word=Gianvito%20Rossi",
        "Gienchi" : "/search/?m=2&word=Gienchi",
        "Giorgio Armani" : "/search/?m=2&word=Giorgio%20Armani",
        "Girl. By Band of Outsiders" : "/search/?m=2&word=Girl.%20By%20Band%20of%20Outsiders",
        "Giuseppe Zanotti" : "/search/?m=2&word=Giuseppe%20Zanotti",
        "Givenchy" : "/search/?m=2&word=Givenchy",
        "Glamorous" : "/search/?m=2&word=Glamorous"
    },
    "H" : {
        "HATCH" : "/search/?m=2&word=HATCH",
        "Haider Ackermann" : "/search/?m=2&word=Haider%20Ackermann",
        "Halston Heritage" : "/search/?m=2&word=Halston%20Heritage",
        "Haute Hippie" : "/search/?m=2&word=Haute%20Hippie",
        "Havaianas" : "/search/?m=2&word=Havaianas",
        "Heather" : "/search/?m=2&word=Heather",
        "Heidi Klein" : "/search/?m=2&word=Heidi%20Klein",
        "Helmut Lang" : "/search/?m=2&word=Helmut%20Lang",
        "Herschel" : "/search/?m=2&word=Herschel",
        "Hervé Léger" : "/search/?m=2&word=Herv%C3%A9%20L%C3%A9ger",
        "Hide" : "/search/?m=2&word=Hide",
        "Hobbs" : "/search/?m=2&word=Hobbs",
        "Hoss Intropia" : "/search/?m=2&word=Hoss%20Intropia",
        "House Of Hackney" : "/search/?m=2&word=House%20Of%20Hackney",
        "House Of Holland" : "/search/?m=2&word=House%20Of%20Holland",
        "Hudson" : "/search/?m=2&word=Hudson",
        "Hunter" : "/search/?m=2&word=Hunter"
    },
    "I" : {
        "IRO" : "/search/?m=2&word=IRO",
        "ISSA" : "/search/?m=2&word=ISSA"
    },
    "J" : {
        "J Brand" : "/search/?m=2&word=J%20Brand",
        "J Brand Denim" : "/search/?m=2&word=J%20Brand%20Denim",
        "J.Crew" : "/search/?m=2&word=J.Crew",
        "J.W. Anderson" : "/search/?m=2&word=J.W.%20Anderson",
        "James Perse" : "/search/?m=2&word=James%20Perse",
        "Jason Wu" : "/search/?m=2&word=Jason%20Wu",
        "Jean Paul Gaultier" : "/search/?m=2&word=Jean%20Paul%20Gaultier",
        "Jeffrey Campbell" : "/search/?m=2&word=Jeffrey%20Campbell",
        "Jessica Simpson" : "/search/?m=2&word=Jessica%20Simpson",
        "Jil Sander" : "/search/?m=2&word=Jil%20Sander",
        "Jil Sander Navy" : "/search/?m=2&word=Jil%20Sander%20Navy",
        "Jimmy Choo" : "/search/?m=2&word=Jimmy%20Choo",
        "Joe's jeans" : "/search/?m=2&word=Joe%27s%20jeans",
        "John Galliano" : "/search/?m=2&word=John%20Galliano",
        "Joie" : "/search/?m=2&word=Joie",
        "Jonathan Adler" : "/search/?m=2&word=Jonathan%20Adler",
        "Jonathan Saunders" : "/search/?m=2&word=Jonathan%20Saunders",
        "Jonathan Simkhai" : "/search/?m=2&word=Jonathan%20Simkhai",
        "Joseph" : "/search/?m=2&word=Joseph",
        "Josie Natori" : "/search/?m=2&word=Josie%20Natori",
        "Joyrich" : "/search/?m=2&word=Joyrich",
        "JuJu" : "/search/?m=2&word=JuJu",
        "Juicy Couture" : "/search/?m=2&word=Juicy%20Couture",
        "Julian Fashion" : "/search/?m=2&word=Julian%20Fashion",
        "Junya Watanabe" : "/search/?m=2&word=Junya%20Watanabe",
        "Just Cavalli" : "/search/?m=2&word=Just%20Cavalli"
    },
    "K" : {
        "K. Jacques" : "/search/?m=2&word=K.%20Jacques",
        "KENZO" : "/search/?m=2&word=KENZO",
        "KG by Kurt Geiger" : "/search/?m=2&word=KG%20by%20Kurt%20Geiger",
        "KTZ" : "/search/?m=2&word=KTZ",
        "Karen Millen" : "/search/?m=2&word=Karen%20Millen",
        "Karl Lagerfeld" : "/search/?m=2&word=Karl%20Lagerfeld",
        "Kate Spade" : "/search/?m=2&word=Kate%20Spade",
        "Keds" : "/search/?m=2&word=Keds",
        "Kenneth Jay Lane" : "/search/?m=2&word=Kenneth%20Jay%20Lane",
        "Kiki de Montparnasse" : "/search/?m=2&word=Kiki%20de%20Montparnasse",
        "Kotur" : "/search/?m=2&word=Kotur"
    },
    "L" : {
        "L&#39;Wren Scott" : "/search/?m=2&word=L%26%2339%3BWren%20Scott",
        "L'AGENCE" : "/search/?m=2&word=L%27AGENCE",
        "L'Eclaireur" : "/search/?m=2&word=L%27Eclaireur",
        "LN-CC" : "/search/?m=2&word=LN-CC",
        "LOEWE" : "/search/?m=2&word=LOEWE",
        "Lafayette 148 New York" : "/search/?m=2&word=Lafayette%20148%20New%20York",
        "Lanvin" : "/search/?m=2&word=Lanvin",
        "Lead" : "/search/?m=2&word=Lead",
        "Lela Rose" : "/search/?m=2&word=Lela%20Rose",
        "Levi's" : "/search/?m=2&word=Levi%27s",
        "Lilly Pulitzer" : "/search/?m=2&word=Lilly%20Pulitzer",
        "Linda Farrow" : "/search/?m=2&word=Linda%20Farrow",
        "Line & Dot" : "/search/?m=2&word=Line%20%26%20Dot",
        "Lipsy" : "/search/?m=2&word=Lipsy",
        "Lisa Marie Fernandez" : "/search/?m=2&word=Lisa%20Marie%20Fernandez",
        "Loeffler Randall" : "/search/?m=2&word=Loeffler%20Randall",
        "Longchamp" : "/search/?m=2&word=Longchamp",
        "Loriblu" : "/search/?m=2&word=Loriblu",
        "Louis Vuitton" : "/search/?m=2&word=Louis%20Vuitton",
        "Love Leather" : "/search/?m=2&word=Love%20Leather",
        "Love Moschino" : "/search/?m=2&word=Love%20Moschino",
        "Lover" : "/search/?m=2&word=Lover",
        "Lulu Frost" : "/search/?m=2&word=Lulu%20Frost"
    },
    "M" : {
        "M Missoni" : "/search/?m=2&word=M%20Missoni",
        "MANGO" : "/search/?m=2&word=MANGO",
        "MINKPINK" : "/search/?m=2&word=MINKPINK",
        "MISSONI" : "/search/?m=2&word=MISSONI",
        "MM6 Maison Martin Margiela" : "/search/?m=2&word=MM6%20Maison%20Martin%20Margiela",
        "MSGM" : "/search/?m=2&word=MSGM",
        "Macy's" : "/search/?m=2&word=Macy%27s",
        "Mademoiselle Tara" : "/search/?m=2&word=Mademoiselle%20Tara",
        "Madewell" : "/search/?m=2&word=Madewell",
        "Magic" : "/search/?m=2&word=Magic",
        "Maison Boinet" : "/search/?m=2&word=Maison%20Boinet",
        "Maison Martin Margiela" : "/search/?m=2&word=Maison%20Martin%20Margiela",
        "Maje" : "/search/?m=2&word=Maje",
        "Manolo Blahnik" : "/search/?m=2&word=Manolo%20Blahnik",
        "Mara Hoffman" : "/search/?m=2&word=Mara%20Hoffman",
        "Marc by Marc Jacobs" : "/search/?m=2&word=Marc%20by%20Marc%20Jacobs",
        "Marchesa" : "/search/?m=2&word=Marchesa",
        "Marie Turnor Accessories" : "/search/?m=2&word=Marie%20Turnor%20Accessories",
        "Markus Lupfer" : "/search/?m=2&word=Markus%20Lupfer",
        "Marni" : "/search/?m=2&word=Marni",
        "Marques' Almeida" : "/search/?m=2&word=Marques%27%20Almeida",
        "Martin Grant" : "/search/?m=2&word=Martin%20Grant",
        "Mary Katrantzou" : "/search/?m=2&word=Mary%20Katrantzou",
        "Mason by Michelle Mason" : "/search/?m=2&word=Mason%20by%20Michelle%20Mason",
        "Matthew Williamson" : "/search/?m=2&word=Matthew%20Williamson",
        "MaxMara" : "/search/?m=2&word=MaxMara",
        "May" : "/search/?m=2&word=May",
        "Melissa" : "/search/?m=2&word=Melissa",
        "Melissa Odabash" : "/search/?m=2&word=Melissa%20Odabash",
        "Meredith Wendell" : "/search/?m=2&word=Meredith%20Wendell",
        "MiH Jeans" : "/search/?m=2&word=MiH%20Jeans",
        "Michael Kors" : "/search/?m=2&word=Michael%20Kors",
        "Miguelina" : "/search/?m=2&word=Miguelina",
        "Mikoh" : "/search/?m=2&word=Mikoh",
        "Milly" : "/search/?m=2&word=Milly",
        "Miu Miu" : "/search/?m=2&word=Miu%20Miu",
        "Moda Operandi" : "/search/?m=2&word=Moda%20Operandi",
        "Moncler" : "/search/?m=2&word=Moncler",
        "Monica Vinader" : "/search/?m=2&word=Monica%20Vinader",
        "Montaign" : "/search/?m=2&word=Montaign",
        "Moschino" : "/search/?m=2&word=Moschino",
        "Moschino Cheap & Chic" : "/search/?m=2&word=Moschino%20Cheap%20%26amp%3B%20Chic",
        "Motel" : "/search/?m=2&word=Motel",
        "Mother" : "/search/?m=2&word=Mother",
        "Mother of Pearl" : "/search/?m=2&word=Mother%20of%20Pearl",
        "Mulberry" : "/search/?m=2&word=Mulberry",
        "meli melo" : "/search/?m=2&word=meli%20melo"
    },
    "N" : {
        "NW3 by Hobbs" : "/search/?m=2&word=NW3%20by%20Hobbs",
        "Nancy Gonzalez" : "/search/?m=2&word=Nancy%20Gonzalez",
        "Nanette Lepore" : "/search/?m=2&word=Nanette%20Lepore",
        "Nasty Gal" : "/search/?m=2&word=Nasty%20Gal",
        "Needle & Thread" : "/search/?m=2&word=Needle%20%26%20Thread",
        "New Balance" : "/search/?m=2&word=New%20Balance",
        "New Look" : "/search/?m=2&word=New%20Look",
        "Nicholas Kirkwood" : "/search/?m=2&word=Nicholas%20Kirkwood",
        "Nicole Farhi" : "/search/?m=2&word=Nicole%20Farhi",
        "Nike" : "/search/?m=2&word=Nike",
        "Nina Ricci" : "/search/?m=2&word=Nina%20Ricci",
        "No. 21" : "/search/?m=2&word=No.%2021",
        "Nordstrom" : "/search/?m=2&word=Nordstrom",
        "Norma Kamali" : "/search/?m=2&word=Norma%20Kamali",
        "Notte by Marchesa" : "/search/?m=2&word=Notte%20by%20Marchesa"
    },
    "O" : {
        "OAK" : "/search/?m=2&word=OAK",
        "ONE by" : "/search/?m=2&word=ONE%20by",
        "Oasis" : "/search/?m=2&word=Oasis",
        "Ohne Titel" : "/search/?m=2&word=Ohne%20Titel",
        "Old Navy" : "/search/?m=2&word=Old%20Navy",
        "One Teaspoon" : "/search/?m=2&word=One%20Teaspoon",
        "Opening Ceremony" : "/search/?m=2&word=Opening%20Ceremony",
        "Orla Kiely" : "/search/?m=2&word=Orla%20Kiely",
        "Oscar de la Renta's" : "/search/?m=2&word=Oscar%20de%20la%20Renta%27s",
        "Ostwald Helgason" : "/search/?m=2&word=Ostwald%20Helgason",
        "Outnet" : "/search/?m=2&word=Outnet",
        "Owl" : "/search/?m=2&word=Owl",
        "Oxygen Boutique" : "/search/?m=2&word=Oxygen%20Boutique"
    },
    "P" : {
        "PHILOSOPHY" : "/search/?m=2&word=PHILOSOPHY",
        "Paige" : "/search/?m=2&word=Paige",
        "Paige Denim" : "/search/?m=2&word=Paige%20Denim",
        "Pamela Love" : "/search/?m=2&word=Pamela%20Love",
        "Parker" : "/search/?m=2&word=Parker",
        "Patagonia" : "/search/?m=2&word=Patagonia",
        "Patrizia Pepe" : "/search/?m=2&word=Patrizia%20Pepe",
        "Paul & Joe Sister" : "/search/?m=2&word=Paul%20%26%20Joe%20Sister",
        "Paul Smith" : "/search/?m=2&word=Paul%20Smith",
        "Pencey Standard" : "/search/?m=2&word=Pencey%20Standard",
        "Pepe Jeans" : "/search/?m=2&word=Pepe%20Jeans",
        "Peter Jensen" : "/search/?m=2&word=Peter%20Jensen",
        "Peter Pilotto" : "/search/?m=2&word=Peter%20Pilotto",
        "Piamita" : "/search/?m=2&word=Piamita",
        "Pieces" : "/search/?m=2&word=Pieces",
        "Pierre Hardy" : "/search/?m=2&word=Pierre%20Hardy",
        "Pour La Victoire" : "/search/?m=2&word=Pour%20La%20Victoire",
        "Prabal Gurung" : "/search/?m=2&word=Prabal%20Gurung",
        "Prada" : "/search/?m=2&word=Prada",
        "Preen by Thornton Bregazzi" : "/search/?m=2&word=Preen%20by%20Thornton%20Bregazzi",
        "Prism" : "/search/?m=2&word=Prism",
        "Proenza Schouler" : "/search/?m=2&word=Proenza%20Schouler",
        "Puma" : "/search/?m=2&word=Puma"
    },
    "Q" : {
        "QUINN" : "/search/?m=2&word=QUINN"
    },
    "R" : {
        "R13" : "/search/?m=2&word=R13",
        "RAOUL" : "/search/?m=2&word=RAOUL",
        "RAXEVSKY" : "/search/?m=2&word=RAXEVSKY",
        "REISS" : "/search/?m=2&word=REISS",
        "Rachael Ruddick" : "/search/?m=2&word=Rachael%20Ruddick",
        "Rachel Comey" : "/search/?m=2&word=Rachel%20Comey",
        "Rachel Roy" : "/search/?m=2&word=Rachel%20Roy",
        "Rachel Zoe" : "/search/?m=2&word=Rachel%20Zoe",
        "Rag & bone" : "/search/?m=2&word=Rag%20%26amp%3B%20bone",
        "Ralph Lauren" : "/search/?m=2&word=Ralph%20Lauren",
        "Ralph Lauren Black Label" : "/search/?m=2&word=Ralph%20Lauren%20Black%20Label",
        "Ralph Lauren Blue Label" : "/search/?m=2&word=Ralph%20Lauren%20Blue%20Label",
        "Ralph Lauren Collection" : "/search/?m=2&word=Ralph%20Lauren%20Collection",
        "Raquel Allegra" : "/search/?m=2&word=Raquel%20Allegra",
        "Rare" : "/search/?m=2&word=Rare",
        "Reason" : "/search/?m=2&word=Reason",
        "Rebecca Minkoff" : "/search/?m=2&word=Rebecca%20Minkoff",
        "Rebecca Taylor" : "/search/?m=2&word=Rebecca%20Taylor",
        "Reed Krakoff" : "/search/?m=2&word=Reed%20Krakoff",
        "Relic" : "/search/?m=2&word=Relic",
        "Religion" : "/search/?m=2&word=Religion",
        "Repetto" : "/search/?m=2&word=Repetto",
        "Reverse" : "/search/?m=2&word=Reverse",
        "Rich & Skinny" : "/search/?m=2&word=Rich%20%26%20Skinny",
        "Rick Owens" : "/search/?m=2&word=Rick%20Owens",
        "River Island" : "/search/?m=2&word=River%20Island",
        "Robert Clergerie" : "/search/?m=2&word=Robert%20Clergerie",
        "Robert Rodriguez" : "/search/?m=2&word=Robert%20Rodriguez",
        "Roberto Cavalli" : "/search/?m=2&word=Roberto%20Cavalli",
        "Rochas" : "/search/?m=2&word=Rochas",
        "Roksanda Ilincic" : "/search/?m=2&word=Roksanda%20Ilincic",
        "Roland Mouret" : "/search/?m=2&word=Roland%20Mouret",
        "Romwe" : "/search/?m=2&word=Romwe",
        "Rory Beca" : "/search/?m=2&word=Rory%20Beca",
        "Roxy" : "/search/?m=2&word=Roxy",
        "Rupert Sanderson" : "/search/?m=2&word=Rupert%20Sanderson"
    },
    "S" : {
        "SAM." : "/search/?m=2&word=SAM.",
        "SOLOW" : "/search/?m=2&word=SOLOW",
        "SSENSE" : "/search/?m=2&word=SSENSE",
        "STANCE" : "/search/?m=2&word=STANCE",
        "SUNO" : "/search/?m=2&word=SUNO",
        "Sacai" : "/search/?m=2&word=Sacai",
        "Saint Laurent" : "/search/?m=2&word=Saint%20Laurent",
        "Saloni" : "/search/?m=2&word=Saloni",
        "Salvatore Ferragamo" : "/search/?m=2&word=Salvatore%20Ferragamo",
        "Sam Edelman" : "/search/?m=2&word=Sam%20Edelman",
        "Schutz" : "/search/?m=2&word=Schutz",
        "Sea" : "/search/?m=2&word=Sea",
        "See by Chlo&#233;" : "/search/?m=2&word=See%20by%20Chlo%26%23233%3B",
        "Senso" : "/search/?m=2&word=Senso",
        "Sergio Rossi" : "/search/?m=2&word=Sergio%20Rossi",
        "Sessun" : "/search/?m=2&word=Sessun",
        "SheInside" : "/search/?m=2&word=SheInside",
        "Shine" : "/search/?m=2&word=Shine",
        "Shoshanna" : "/search/?m=2&word=Shoshanna",
        "Sigerson Morrison" : "/search/?m=2&word=Sigerson%20Morrison",
        "Simone Rocha" : "/search/?m=2&word=Simone%20Rocha",
        "Siwy" : "/search/?m=2&word=Siwy",
        "Skin" : "/search/?m=2&word=Skin",
        "Smythson" : "/search/?m=2&word=Smythson",
        "Sonia Rykiel" : "/search/?m=2&word=Sonia%20Rykiel",
        "Sophia Webster" : "/search/?m=2&word=Sophia%20Webster",
        "Sophie Hulme" : "/search/?m=2&word=Sophie%20Hulme",
        "Splendid" : "/search/?m=2&word=Splendid",
        "St. John" : "/search/?m=2&word=St.%20John",
        "Stella Jean" : "/search/?m=2&word=Stella%20Jean",
        "Stella McCartney" : "/search/?m=2&word=Stella%20McCartney",
        "Steve Madden" : "/search/?m=2&word=Steve%20Madden",
        "Steven" : "/search/?m=2&word=Steven",
        "Stuart Weitzman" : "/search/?m=2&word=Stuart%20Weitzman",
        "Stylebop" : "/search/?m=2&word=Stylebop",
        "Superdry" : "/search/?m=2&word=Superdry",
        "Superga" : "/search/?m=2&word=Superga",
        "Swarovski" : "/search/?m=2&word=Swarovski",
        "sass & bide" : "/search/?m=2&word=sass%20%26%20bide"
    },
    "T" : {
        "T by Alexander Wang" : "/search/?m=2&word=T%20by%20Alexander%20Wang",
        "Ted Baker" : "/search/?m=2&word=Ted%20Baker",
        "Temperley London" : "/search/?m=2&word=Temperley%20London",
        "Tess Giberson" : "/search/?m=2&word=Tess%20Giberson",
        "Thakoon" : "/search/?m=2&word=Thakoon",
        "Theory" : "/search/?m=2&word=Theory",
        "Theyskens' Theory" : "/search/?m=2&word=Theyskens%27%20Theory",
        "This Works" : "/search/?m=2&word=This%20Works",
        "Thread" : "/search/?m=2&word=Thread",
        "Three Floor" : "/search/?m=2&word=Three%20Floor",
        "Tibi" : "/search/?m=2&word=Tibi",
        "Tod's" : "/search/?m=2&word=Tod%27s",
        "Toga" : "/search/?m=2&word=Toga",
        "Tommy Hilfiger" : "/search/?m=2&word=Tommy%20Hilfiger",
        "Topshop" : "/search/?m=2&word=Topshop",
        "Torn by Ronny Kobo" : "/search/?m=2&word=Torn%20by%20Ronny%20Kobo",
        "Tory Burch" : "/search/?m=2&word=Tory%20Burch",
        "True Religion|Jayde" : "/search/?m=2&word=True%20Religion%7CJayde",
        "Twelfth St. by Cynthia Vincent" : "/search/?m=2&word=Twelfth%20St.%20by%20Cynthia%20Vincent"
    },
    "U" : {
        "UGG" : "/search/?m=2&word=UGG"
    },
    "V" : {
        "VIKTOR & ROLF" : "/search/?m=2&word=VIKTOR%20%26%20ROLF",
        "Vagabond" : "/search/?m=2&word=Vagabond",
        "Valentino" : "/search/?m=2&word=Valentino",
        "Vanessa Bruno" : "/search/?m=2&word=Vanessa%20Bruno",
        "Vanessa Bruno Athe" : "/search/?m=2&word=Vanessa%20Bruno%20Athe",
        "Vera Wang" : "/search/?m=2&word=Vera%20Wang",
        "Versace" : "/search/?m=2&word=Versace",
        "VeryEICKHOFF" : "/search/?m=2&word=VeryEICKHOFF",
        "Victoria Beckham" : "/search/?m=2&word=Victoria%20Beckham",
        "Vila" : "/search/?m=2&word=Vila",
        "Vince" : "/search/?m=2&word=Vince",
        "Vionnet" : "/search/?m=2&word=Vionnet",
        "Virgos Lounge" : "/search/?m=2&word=Virgos%20Lounge",
        "Vivienne Westwood" : "/search/?m=2&word=Vivienne%20Westwood",
        "Vix" : "/search/?m=2&word=Vix",
        "Vix Swimwear" : "/search/?m=2&word=Vix%20Swimwear"
    },
    "W" : {
        "We Are Handsome" : "/search/?m=2&word=We%20Are%20Handsome",
        "Whistles" : "/search/?m=2&word=Whistles",
        "Wildfox Couture" : "/search/?m=2&word=Wildfox%20Couture",
        "Willow" : "/search/?m=2&word=Willow",
        "Wilt" : "/search/?m=2&word=Wilt",
        "Won Hundred" : "/search/?m=2&word=Won%20Hundred",
        "Wood Wood" : "/search/?m=2&word=Wood%20Wood",
        "Worn By" : "/search/?m=2&word=Worn%20By",
        "Wrangler" : "/search/?m=2&word=Wrangler"
    },
    "Y" : {
        "Y.A.S" : "/search/?m=2&word=Y.A.S",
        "YSL" : "/search/?m=2&word=YSL",
        "Yoox" : "/search/?m=2&word=Yoox",
        "Young Fabulous & Broke" : "/search/?m=2&word=Young%20Fabulous%20%26amp%3B%20Broke"
    },
    "Z" : {
        "ZOE KARSSEN" : "/search/?m=2&word=ZOE%20KARSSEN",
        "Zac Posen" : "/search/?m=2&word=Zac%20Posen",
        "Zara" : "/search/?m=2&word=Zara",
        "Zimmermann" : "/search/?m=2&word=Zimmermann"
    }
}